umu_commander/__init__.py
umu_commander/__main__.py
umu_commander/classes.py
umu_commander/configuration.py
umu_commander/database.py
umu_commander/proton.py
umu_commander/tracking.py
umu_commander/umu_config.py
umu_commander/util.py
umu_commander-1.7.0.dist-info/METADATA
umu_commander-1.7.0.dist-info/WHEEL
umu_commander-1.7.0.dist-info/entry_points.txt
umu_commander-1.7.0.dist-info/licenses/LICENSE.txt
umu_commander-1.7.0.dist-info/RECORD
