Metadata-Version: 2.4
Name: umu-commander
Version: 1.7.0
Summary: umu-commander is an interactive CLI tool to help you manage umu.
Project-URL: Homepage, https://github.com/Mpaxlamitsounas/umu-commander
Project-URL: Issues, https://github.com/Mpaxlamitsounas/umu-commander/issues
Author-email: Mpaxlamitsounas <worldstudy123@gmail.com>
License-Expression: MIT
License-File: LICENSE.txt
Keywords: umu,umu-launcher
Classifier: Operating System :: POSIX :: Linux
Classifier: Programming Language :: Python :: 3
Requires-Python: >=3.12
Requires-Dist: inquirerpy
Requires-Dist: tomli-w
